atomlite/__init__.py
atomlite/py.typed
atomlite/_internal/__init__.py
atomlite/_internal/database.py
atomlite/_internal/json.py
atomlite/_internal/scripts/__init__.py
atomlite/_internal/scripts/atomlite.py
atomlite-4.5.0.dist-info/licenses/LICENSE
atomlite-4.5.0.dist-info/METADATA
atomlite-4.5.0.dist-info/WHEEL
atomlite-4.5.0.dist-info/entry_points.txt
atomlite-4.5.0.dist-info/top_level.txt
atomlite-4.5.0.dist-info/RECORD
