Metadata-Version: 2.4
Name: atomlite
Version: 4.5.0
Summary: A SQLite chemical database.
Maintainer-email: Lukas Turcani <lukasturcani93@gmail.com>
Project-URL: github, https://github.com/lukasturcani/atomlite
Project-URL: documentation, https://atomlite.readthedocs.io
Requires-Python: >=3.11
License-File: LICENSE
Requires-Dist: polars
Requires-Dist: rdkit>=2024.9.6
Provides-Extra: dev
Requires-Dist: ruff; extra == "dev"
Requires-Dist: mypy; extra == "dev"
Requires-Dist: numpy; extra == "dev"
Requires-Dist: pytest; extra == "dev"
Requires-Dist: pytest-cov; extra == "dev"
Requires-Dist: sphinx; extra == "dev"
Requires-Dist: sphinx-copybutton; extra == "dev"
Requires-Dist: build; extra == "dev"
Requires-Dist: twine; extra == "dev"
Requires-Dist: furo; extra == "dev"
Dynamic: license-file
